aleatools/__init__.py
aleatools/gitaux.py
aleatools/scripts/addgnu.py
aleatools/scripts/cowspeak.py
aleatools/scripts/crypt.py
aleatools/scripts/makegif.py
aleatools/scripts/pullall.py
aleatools/scripts/pushall.py
aleatools/scripts/recode.py
aleatools/scripts/resizeimage.py
aleatools/scripts/resizeimages.py
aleatools/scripts/text2png.py
aleatools-20.2.23.0.data/scripts/addgnu.py
aleatools-20.2.23.0.data/scripts/cowspeak.py
aleatools-20.2.23.0.data/scripts/crypt.py
aleatools-20.2.23.0.data/scripts/makegif.py
aleatools-20.2.23.0.data/scripts/pullall.py
aleatools-20.2.23.0.data/scripts/pushall.py
aleatools-20.2.23.0.data/scripts/recode.py
aleatools-20.2.23.0.data/scripts/resizeimage.py
aleatools-20.2.23.0.data/scripts/resizeimages.py
aleatools-20.2.23.0.data/scripts/text2png.py
aleatools-20.2.23.0.dist-info/METADATA
aleatools-20.2.23.0.dist-info/WHEEL
aleatools-20.2.23.0.dist-info/top_level.txt
aleatools-20.2.23.0.dist-info/RECORD
